winpwn/__init__.py
winpwn/asm.py
winpwn/context.py
winpwn/dbg.py
winpwn/misc.py
winpwn/win.py
winpwn/wincs.py
winpwn/winfile.py
winpwn/winpwn.py
wpwn/__init__.py
wpwn/asm.py
wpwn/context.py
wpwn/dbg.py
wpwn/misc.py
wpwn/win.py
wpwn/wincs.py
wpwn/winfile.py
wpwn/winpwn.py
wpwn-1.0.0.dist-info/METADATA
wpwn-1.0.0.dist-info/WHEEL
wpwn-1.0.0.dist-info/top_level.txt
wpwn-1.0.0.dist-info/RECORD
