Metadata-Version: 2.1
Name: wpwn
Version: 1.0.0
Summary: windows pwntools
Home-page: https://github.com/qwerty-po/winpwn
Author: qwerty
Author-email: qw3rtyp0@gmail.com
License: MIT
Platform: UNKNOWN
Requires-Dist: lief
Requires-Dist: capstone
Requires-Dist: keystone
